vncuda/CTPMarket.py
vncuda/CTPMarketType.py
vncuda/__init__.py
vncuda/globalType.py
vncuda/globalvar.py
vncuda/main.py
vnhub-1.0.dist-info/LICENSE
vnhub-1.0.dist-info/METADATA
vnhub-1.0.dist-info/WHEEL
vnhub-1.0.dist-info/top_level.txt
vnhub-1.0.dist-info/RECORD
